person_detector/__init__.py
person_detector/detector.py
person_detector/main.py
person_detector/tracker.py
person_detector/utils/__init__.py
person_detector/utils/datetime_utils.py
person_detector/utils/enums.py
person_detector/utils/image_utils.py
person_detector-0.0.5.dist-info/LICENSE.md
person_detector-0.0.5.dist-info/METADATA
person_detector-0.0.5.dist-info/WHEEL
person_detector-0.0.5.dist-info/top_level.txt
person_detector-0.0.5.dist-info/RECORD
