Metadata-Version: 2.1
Name: person_detector
Version: 0.0.5
Summary: A high level API for detecting and tracking people.
Author-email: k3y5tr0k3 <k3y5tr0k3.software@gmail.com>
Project-URL: Homepage, https://github.com/k3y5tr0k3/person-detector
Project-URL: Issues, https://github.com/k3y5tr0k3/person-detector/issues
Classifier: Programming Language :: Python :: 3
Classifier: License :: OSI Approved :: GNU Affero General Public License v3
Classifier: Operating System :: OS Independent
Requires-Python: >=3.10
License-File: LICENSE.md
Requires-Dist: absl-py ==2.1.0
Requires-Dist: astunparse ==1.6.3
Requires-Dist: certifi ==2024.7.4
Requires-Dist: charset-normalizer ==3.3.2
Requires-Dist: contourpy ==1.2.1
Requires-Dist: cycler ==0.12.1
Requires-Dist: filelock ==3.15.4
Requires-Dist: flatbuffers ==24.3.25
Requires-Dist: fonttools ==4.53.1
Requires-Dist: fsspec ==2024.6.1
Requires-Dist: gast ==0.6.0
Requires-Dist: gitdb ==4.0.11
Requires-Dist: GitPython ==3.1.43
Requires-Dist: google-pasta ==0.2.0
Requires-Dist: grpcio ==1.65.4
Requires-Dist: h5py ==3.11.0
Requires-Dist: idna ==3.7
Requires-Dist: Jinja2 ==3.1.4
Requires-Dist: joblib ==1.4.2
Requires-Dist: keras ==3.4.1
Requires-Dist: kiwisolver ==1.4.5
Requires-Dist: lapx ==0.5.9.post1
Requires-Dist: libclang ==18.1.1
Requires-Dist: Markdown ==3.6
Requires-Dist: markdown-it-py ==3.0.0
Requires-Dist: MarkupSafe ==2.1.5
Requires-Dist: matplotlib ==3.9.1
Requires-Dist: mdurl ==0.1.2
Requires-Dist: ml-dtypes ==0.4.0
Requires-Dist: mpmath ==1.3.0
Requires-Dist: namex ==0.0.8
Requires-Dist: networkx ==3.3
Requires-Dist: numpy ==1.25.2
Requires-Dist: nvidia-cublas-cu12 ==12.1.3.1
Requires-Dist: nvidia-cuda-cupti-cu12 ==12.1.105
Requires-Dist: nvidia-cuda-nvcc-cu12 ==12.3.107
Requires-Dist: nvidia-cuda-nvrtc-cu12 ==12.1.105
Requires-Dist: nvidia-cuda-runtime-cu12 ==12.1.105
Requires-Dist: nvidia-cudnn-cu12 ==9.1.0.70
Requires-Dist: nvidia-cufft-cu12 ==11.0.2.54
Requires-Dist: nvidia-curand-cu12 ==10.3.2.106
Requires-Dist: nvidia-cusolver-cu12 ==11.4.5.107
Requires-Dist: nvidia-cusparse-cu12 ==12.1.0.106
Requires-Dist: nvidia-nccl-cu12 ==2.20.5
Requires-Dist: nvidia-nvjitlink-cu12 ==12.3.101
Requires-Dist: nvidia-nvtx-cu12 ==12.1.105
Requires-Dist: opencv-python ==4.10.0.84
Requires-Dist: opt-einsum ==3.3.0
Requires-Dist: optree ==0.12.1
Requires-Dist: packaging ==24.1
Requires-Dist: pandas ==2.2.2
Requires-Dist: pdoc ==14.6.0
Requires-Dist: pillow ==10.4.0
Requires-Dist: protobuf ==4.25.4
Requires-Dist: psutil ==6.0.0
Requires-Dist: py-cpuinfo ==9.0.0
Requires-Dist: Pygments ==2.18.0
Requires-Dist: pyparsing ==3.1.2
Requires-Dist: python-dateutil ==2.9.0.post0
Requires-Dist: pytz ==2024.1
Requires-Dist: PyYAML ==6.0.1
Requires-Dist: requests ==2.32.3
Requires-Dist: rich ==13.7.1
Requires-Dist: scipy ==1.9.3
Requires-Dist: seaborn ==0.13.2
Requires-Dist: six ==1.16.0
Requires-Dist: sklearn ==0.0.post12
Requires-Dist: smmap ==5.0.1
Requires-Dist: sympy ==1.13.1
Requires-Dist: tensorboard ==2.17.0
Requires-Dist: tensorboard-data-server ==0.7.2
Requires-Dist: tensorflow ==2.17.0
Requires-Dist: tensorflow-io-gcs-filesystem ==0.37.1
Requires-Dist: termcolor ==2.4.0
Requires-Dist: threadpoolctl ==3.5.0
Requires-Dist: torch ==2.4.0
Requires-Dist: torchvision ==0.19.0
Requires-Dist: tqdm ==4.66.5
Requires-Dist: triton ==3.0.0
Requires-Dist: typing-extensions ==4.12.2
Requires-Dist: tzdata ==2024.1
Requires-Dist: ultralytics ==8.2.72
Requires-Dist: ultralytics-thop ==2.0.0
Requires-Dist: urllib3 ==2.2.2
Requires-Dist: Werkzeug ==3.0.3
Requires-Dist: wrapt ==1.16.0
